lucaciucci/__init__.py
lucaciucci/uni/__init__.py
lucaciucci/uni/lab2/__init__.py
lucaciucci/uni/lab2/figures.py
lucaciucci/uni/lab2/lab2.py
lucaciucci/uni/lab2/load_data.py
lucaciucci-0.0.7.dist-info/LICENSE
lucaciucci-0.0.7.dist-info/METADATA
lucaciucci-0.0.7.dist-info/WHEEL
lucaciucci-0.0.7.dist-info/top_level.txt
lucaciucci-0.0.7.dist-info/RECORD
