Metadata-Version: 2.1
Name: lucaciucci
Version: 0.0.7
Summary: Still empty
Home-page: https://github.com/LucaCiucci/lucaciucci
Author: Luca Ciucci
Author-email: develp@lucaciucci99.com
License: UNKNOWN
Platform: UNKNOWN
Classifier: Programming Language :: Python :: 3
Classifier: License :: OSI Approved :: MIT License
Classifier: Operating System :: OS Independent
Requires-Python: >=3.6
